[
    {
        "id": 1,
        "first_name": "Quentin",
        "last_name": "Murfett",
        "email": "qmurfett0@ehow.com"
    },
    {
        "id": 2,
        "first_name": "Federica",
        "last_name": "Dudin",
        "email": "fdudin1@ca.gov"
    },
    {
        "id": 3,
        "first_name": "Jonis",
        "last_name": "Korejs",
        "email": "jkorejs2@opera.com"
    },
    {
        "id": 4,
        "first_name": "Luz",
        "last_name": "Gonnely",
        "email": "lgonnely3@imgur.com"
    },
    {
        "id": 5,
        "first_name": "Sibella",
        "last_name": "Upsale",
        "email": "supsale4@howstuffworks.com"
    },
    {
        "id": 6,
        "first_name": "Efren",
        "last_name": "Belden",
        "email": "ebelden5@g.co"
    },
    {
        "id": 7,
        "first_name": "Gilly",
        "last_name": "MacKellar",
        "email": "gmackellar6@howstuffworks.com"
    },
    {
        "id": 8,
        "first_name": "Laurie",
        "last_name": "Rasp",
        "email": "lrasp7@deliciousdays.com"
    },
    {
        "id": 9,
        "first_name": "Alyosha",
        "last_name": "Sein",
        "email": "asein8@yandex.ru"
    },
    {
        "id": 10,
        "first_name": "Hastie",
        "last_name": "Edinburgh",
        "email": "hedinburgh9@google.com"
    },
    {
        "id": 11,
        "first_name": "Gael",
        "last_name": "de Chastelain",
        "email": "gdechastelaina@reddit.com"
    },
    {
        "id": 12,
        "first_name": "Freedman",
        "last_name": "Laste",
        "email": "flasteb@businessinsider.com"
    },
    {
        "id": 13,
        "first_name": "Kassi",
        "last_name": "Hoyland",
        "email": "khoylandc@china.com.cn"
    },
    {
        "id": 14,
        "first_name": "Westley",
        "last_name": "Ledgerton",
        "email": "wledgertond@photobucket.com"
    },
    {
        "id": 15,
        "first_name": "Whit",
        "last_name": "Dugall",
        "email": "wdugalle@google.com"
    },
    {
        "id": 16,
        "first_name": "Gunar",
        "last_name": "Heliet",
        "email": "ghelietf@sina.com.cn"
    },
    {
        "id": 17,
        "first_name": "Leola",
        "last_name": "Samme",
        "email": "lsammeg@ucsd.edu"
    },
    {
        "id": 18,
        "first_name": "Danella",
        "last_name": "Wicks",
        "email": "dwicksh@theguardian.com"
    },
    {
        "id": 19,
        "first_name": "Tarrah",
        "last_name": "De Giorgis",
        "email": "tdegiorgisi@narod.ru"
    },
    {
        "id": 20,
        "first_name": "Kerwin",
        "last_name": "Lindstedt",
        "email": "klindstedtj@furl.net"
    }
]